setup.py
validator_sa/__init__.py
validator_sa/package_authentication.py
validator_sa/validator_sahala.py
validator_sa.egg-info/PKG-INFO
validator_sa.egg-info/SOURCES.txt
validator_sa.egg-info/dependency_links.txt
validator_sa.egg-info/requires.txt
validator_sa.egg-info/top_level.txt