Metadata-Version: 1.0
Name: validator-sa
Version: 0.4
Summary: 数据校验器：dict,list等python任何数据类型
Home-page: https://github.com/
Author: liyubin
Author-email: 1399393088@qq.com
License: MIT Licence
Keywords: pip,validator_sa,featureextraction
Platform: any
